oriloc/__init__.py
oriloc-0.0.2.dist-info/LICENSE.txt
oriloc-0.0.2.dist-info/METADATA
oriloc-0.0.2.dist-info/WHEEL
oriloc-0.0.2.dist-info/top_level.txt
oriloc-0.0.2.dist-info/RECORD
