Metadata-Version: 2.1
Name: oriloc
Version: 0.0.2
Summary: A package for location
Home-page: https://github.com/HOKOTATE-pzw/oriloc.git
Author: HOKOTATE
Author-email: pangzewei2010@foxmail.com
License: MIT
Platform: UNKNOWN
Classifier: License :: OSI Approved :: MIT License
Classifier: Programming Language :: Python
Classifier: Programming Language :: Python :: 3
Classifier: Programming Language :: Python :: 3.10
Classifier: Programming Language :: Python :: Implementation :: CPython
Classifier: Programming Language :: Python :: Implementation :: PyPy
Requires-Python: >=3.6.0
License-File: LICENSE.txt
Requires-Dist: numpy
